MANIFEST.in
setup.py
api/__init__.py
api/c4.py
api/chunk.py
api/common.py
api/dm.py
api/es.py
api/feishu.py
api/mynac.py
api/sntjson-es.py
api/sqlite.py
api/wget.py
app/__init__.py
app/dmdsk/__init__.py
app/dmdsk/app_navbar.py
app/dmdsk/index.py
app/dmdsk/func/__init__.py
app/dmdsk/func/dim-awl.py
app/dmdsk/func/dims.py
app/dmdsk/func/eidv.py
app/dmdsk/func/feedback.py
app/dmdsk/func/info.py
app/dmdsk/func/lemma.py
app/dmdsk/func/scores.py
app/dmdsk/func/sent.py
app/dmdsk/func/trp.py
cikuu.egg-info/PKG-INFO
cikuu.egg-info/SOURCES.txt
cikuu.egg-info/dependency_links.txt
cikuu.egg-info/requires.txt
cikuu.egg-info/top_level.txt
dic/__init__.py
dic/__main__.py
dic/adjlist.py
dic/advlist.py
dic/bnc_wordlist.py
dic/confu_set.py
dic/ecdic.py
dic/errants.py
dic/essays.py
dic/frame.py
dic/lemma_lex.py
dic/lemma_mf.py
dic/lemma_scale.py
dic/lex_lemma.py
dic/mwe_disconj.py
dic/mwe_pv.py
dic/n_is_sb.py
dic/nounlist.py
dic/nyt_wc.py
dic/oneself.py
dic/orals.py
dic/poslist.py
dic/propbank.py
dic/stoplist.py
dic/to_redislite.py
dic/verbform.py
dic/verblist.py
dic/verbtag.py
dic/vocab.py
dic/word_awl.py
dic/word_bits.py
dic/word_grade.py
dic/word_gsl1.py
dic/word_gsl2.py
dic/word_idf.py
dic/word_oov.py
dic/word_pos.py
dic/word_scale.py
dic/wordattr.py
dic/wordcnt.py
dic/wordlist.py
dic/wordlist_ed1.py
dic/wordnet_verb.py
dic/wordpos.py
dic/words.py
dic/yulk.py
dsk/__init__.py
dsk/__main__.py
dsk/common.py
dsk/dm.py
dsk/dsk-hello.py
dsk/dsk-req.py
dsk/dsk-to-dskmkf.py
dsk/dsk2023.py
dsk/dskapi.py
dsk/dskes.py
dsk/dskmkf.py
dsk/dskmkf_fastapi.py
dsk/dsktrain.py
dsk/essaydm.py
dsk/gears-xdsk.py
dsk/gecv1.py
dsk/index.py
dsk/innersim.py
dsk/json-to-dskmkf.py
dsk/kvrdsk.py
dsk/load.py
dsk/mkf.py
dsk/mqconsume.py
dsk/pingyu.py
dsk/score.py
dsk/sntsdims.py
dsk/test.py
dsk/tok-hello.py
dsk/uvidsk.py
dsk/wps-gec.py
dsk/wps-xgec.py
dsk/wps7000.py
dsk/xessay.py
dsk/xgecv1-test.py
dsk/xgecv1.py
dsk/xmkf.py
dsk/xsnt-gec.py
dsk/xsnt-spacy.py
en/__init__.py
en/__main__.py
en/annotate.py
en/c4-cl.py
en/c4-fts.py
en/c4-gram-upload.py
en/c4-gram.py
en/c4-grams.py
en/c4-np.py
en/c4-postag.py
en/c4-trp.py
en/c4cl.py
en/c4down.py
