Metadata-Version: 1.0
Name: cikuu
Version: 2022.8.10
Summary: cikuu tools
Home-page: http://www.cikuu.com
Author: cikuu
Author-email: info@cikuu.com
License: MIT Licence
Keywords: pip
Platform: any
